automatic_api/__init__.py
automatic_api/automatic.py
AutomaticAPI-0.3.dist-info/METADATA
AutomaticAPI-0.3.dist-info/WHEEL
AutomaticAPI-0.3.dist-info/top_level.txt
AutomaticAPI-0.3.dist-info/RECORD
